qpysequence/__init__.py
qpysequence/acquisitions.py
qpysequence/constants.py
qpysequence/enums.py
qpysequence/library.py
qpysequence/logger.py
qpysequence/sequence.py
qpysequence/waveforms.py
qpysequence/weights.py
qpysequence/program/__init__.py
qpysequence/program/block.py
qpysequence/program/component.py
qpysequence/program/infinite_loop.py
qpysequence/program/iterative_loop.py
qpysequence/program/loop.py
qpysequence/program/memory.py
qpysequence/program/nopper.py
qpysequence/program/program.py
qpysequence/program/register.py
qpysequence/program/instructions/__init__.py
qpysequence/program/instructions/instruction.py
qpysequence/program/instructions/arithmetic/__init__.py
qpysequence/program/instructions/arithmetic/_add.py
qpysequence/program/instructions/arithmetic/_and.py
qpysequence/program/instructions/arithmetic/_asl.py
qpysequence/program/instructions/arithmetic/_asr.py
qpysequence/program/instructions/arithmetic/_move.py
qpysequence/program/instructions/arithmetic/_not.py
qpysequence/program/instructions/arithmetic/_or.py
qpysequence/program/instructions/arithmetic/_sub.py
qpysequence/program/instructions/arithmetic/_xor.py
qpysequence/program/instructions/conditional/__init__.py
qpysequence/program/instructions/conditional/_set_cond.py
qpysequence/program/instructions/control/__init__.py
qpysequence/program/instructions/control/_illegal.py
qpysequence/program/instructions/control/_nop.py
qpysequence/program/instructions/control/_stop.py
qpysequence/program/instructions/jumps/__init__.py
qpysequence/program/instructions/jumps/_jge.py
qpysequence/program/instructions/jumps/_jlt.py
qpysequence/program/instructions/jumps/_jmp.py
qpysequence/program/instructions/jumps/_loop.py
qpysequence/program/instructions/parameter_operations/__init__.py
qpysequence/program/instructions/parameter_operations/_reset_ph.py
qpysequence/program/instructions/parameter_operations/_set_awg_gain.py
qpysequence/program/instructions/parameter_operations/_set_awg_offs.py
qpysequence-0.10.8.dist-info/METADATA
qpysequence-0.10.8.dist-info/WHEEL
qpysequence-0.10.8.dist-info/licenses/LICENSE
qpysequence-0.10.8.dist-info/RECORD
