Metadata-Version: 2.4
Name: qpysequence
Version: 0.10.8
Summary: QPySequence, which stands for *Qblox Python Sequence*, is a python library to programmatically create the `sequence.json` file that is uploaded to a Qblox sequencer.
Author-email: Qilimanjaro Quantum Tech <info@qilimanjaro.tech>
License-File: LICENSE
Keywords: q1asm,qblox
Classifier: Development Status :: 5 - Production/Stable
Classifier: Intended Audience :: Developers
Classifier: Intended Audience :: Science/Research
Classifier: Programming Language :: Python :: 3
Classifier: Programming Language :: Python :: 3.10
Classifier: Programming Language :: Python :: 3.11
Classifier: Programming Language :: Python :: 3.12
Classifier: Programming Language :: Python :: 3.13
Classifier: Topic :: Scientific/Engineering :: Physics
Requires-Python: >=3.10
Requires-Dist: loguru>=0.7.3
Requires-Dist: numpy
